{
  "comp-1": {
    "data": [
      "OS:Linux",
      "Location:Lab"
    ],
    "idn": "comp-1",
    "installed_software_idns": [
      "soft-1",
      "soft-2"
    ],
    "network_idn": [
      1,
      2
    ],
    "provides_hardware_quota": 100,
    "software_data_links": {
      "soft-1": [
        "dt-1",
        "dt-2"
      ]
    },
    "software_idn_mapping": {
      "soft-1": "Software One"
    },
    "stored_credentials": [
      "cred-1"
    ],
    "used_hardware_quota": 40,
    "installed_software": {
      "soft-1": {
        "accepts_credentials": [
          "cred-1"
        ],
        "compatible_data_types": [
          "dt-1"
        ],
        "computer_idn": "comp-1",
        "cpe_idn": "cpe:/a:vendor:soft1:1.0",
        "hardware_ids": [
          "hw-1"
        ],
        "idn": "soft-1",
        "idn_variant": "v1.0",
        "installed_combination": [
          [
            "soft-2",
            "L"
          ]
        ],
        "is_database": "0",
        "local_dependencies": [],
        "max_client_count": 100,
        "network_clients": [
          "soft-2"
        ],
        "network_dependencies": [],
        "network_idn": [
          1
        ],
        "network_servers": [
          "srv-db"
        ],
        "person_group_id": null,
        "person_index": 1,
        "provides_network_services": [
          "net-srv-1"
        ],
        "provides_services": [
          "srv-1"
        ],
        "provides_user_services": [
          "user-srv-1"
        ],
        "requires_hardware_quota": 10,
        "requires_hardware_quota_per_client": 0.5
      },
      "soft-2": {
        "accepts_credentials": [
          "cred-1"
        ],
        "compatible_data_types": [
          "dt-2"
        ],
        "computer_idn": "comp-1",
        "cpe_idn": "cpe:/a:vendor:soft2:2.0",
        "hardware_ids": [
          "hw-2"
        ],
        "idn": "soft-2",
        "idn_variant": "v2.0",
        "installed_combination": [
          [
            "soft-1",
            "N"
          ]
        ],
        "is_database": "1",
        "local_dependencies": [],
        "max_client_count": 50,
        "network_clients": [
          "client-app"
        ],
        "network_dependencies": [],
        "network_idn": [
          2
        ],
        "network_servers": [
          "srv-api"
        ],
        "person_group_id": "pg-1",
        "person_index": 2,
        "provides_network_services": [
          "net-srv-2"
        ],
        "provides_services": [
          "srv-2"
        ],
        "provides_user_services": [
          "user-srv-2"
        ],
        "requires_hardware_quota": 5,
        "requires_hardware_quota_per_client": 0.2
      }
    }
  }
}